[
        {
            "Created_Time": null,
            "Created_User": null,
            "Deleted_Indicator": null,
            "Deleted_Time": null,
            "Deleted_User": null,
            "Updated_Time": null,
            "Updated_User": null,
            "airline": "﻿American Airlines",
            "airlinecode": "AA",
            "id": 1,
            "mawb_prefix": "001"
        },
        {
            "Created_Time": null,
            "Created_User": null,
            "Deleted_Indicator": null,
            "Deleted_Time": null,
            "Deleted_User": null,
            "Updated_Time": null,
            "Updated_User": null,
            "airline": "CargoItalia (alternate)",
            "airlinecode": "2G",
            "id": 2,
            "mawb_prefix": "002"
        },
        {
            "Created_Time": null,
            "Created_User": null,
            "Deleted_Indicator": null,
            "Deleted_Time": null,
            "Deleted_User": null,
            "Updated_Time": null,
            "Updated_User": null,
            "airline": "Continental Airlines",
            "airlinecode": "CO",
            "id": 3,
            "mawb_prefix": "005"
        },
        {
            "Created_Time": null,
            "Created_User": null,
            "Deleted_Indicator": null,
            "Deleted_Time": null,
            "Deleted_User": null,
            "Updated_Time": null,
            "Updated_User": null,
            "airline": "Delta Air Lines",
            "airlinecode": "DL",
            "id": 4,
            "mawb_prefix": "006"
        },
        {
            "Created_Time": null,
            "Created_User": null,
            "Deleted_Indicator": null,
            "Deleted_Time": null,
            "Deleted_User": null,
            "Updated_Time": null,
            "Updated_User": null,
            "airline": "Northwest Airlines (alternate site)",
            "airlinecode": "NW",
            "id": 5,
            "mawb_prefix": "012"
        },
        {
            "Created_Time": null,
            "Created_User": null,
            "Deleted_Indicator": null,
            "Deleted_Time": null,
            "Deleted_User": null,
            "Updated_Time": null,
            "Updated_User": null,
            "airline": "Air Canada",
            "airlinecode": "AC",
            "id": 6,
            "mawb_prefix": "014"
        },
        {
            "Created_Time": null,
            "Created_User": null,
            "Deleted_Indicator": null,
            "Deleted_Time": null,
            "Deleted_User": null,
            "Updated_Time": null,
            "Updated_User": null,
            "airline": "United Airlines Cargo",
            "airlinecode": "UA",
            "id": 7,
            "mawb_prefix": "016"
        },
        {
            "Created_Time": null,
            "Created_User": null,
            "Deleted_Indicator": null,
            "Deleted_Time": null,
            "Deleted_User": null,
            "Updated_Time": null,
            "Updated_User": null,
            "airline": "Canadian Airlines Int´l",
            "airlinecode": "CP",
            "id": 8,
            "mawb_prefix": "018"
        },
        {
            "Created_Time": null,
            "Created_User": null,
            "Deleted_Indicator": null,
            "Deleted_Time": null,
            "Deleted_User": null,
            "Updated_Time": null,
            "Updated_User": null,
            "airline": "Lufthansa Cargo AG",
            "airlinecode": "LH",
            "id": 9,
            "mawb_prefix": "020"
        },
        {
            "Created_Time": null,
            "Created_User": null,
            "Deleted_Indicator": null,
            "Deleted_Time": null,
            "Deleted_User": null,
            "Updated_Time": null,
            "Updated_User": null,
            "airline": "Fedex",
            "airlinecode": "FX",
            "id": 10,
            "mawb_prefix": "023"
        },
        {
            "Created_Time": null,
            "Created_User": null,
            "Deleted_Indicator": null,
            "Deleted_Time": null,
            "Deleted_User": null,
            "Updated_Time": null,
            "Updated_User": null,
            "airline": "Alaska Airlines",
            "airlinecode": "AS",
            "id": 11,
            "mawb_prefix": "027"
        },
        {
            "Created_Time": null,
            "Created_User": null,
            "Deleted_Indicator": null,
            "Deleted_Time": null,
            "Deleted_User": null,
            "Updated_Time": null,
            "Updated_User": null,
            "airline": "USAirways",
            "airlinecode": "US",
            "id": 12,
            "mawb_prefix": "037"
        },
        {
            "Created_Time": null,
            "Created_User": null,
            "Deleted_Indicator": null,
            "Deleted_Time": null,
            "Deleted_User": null,
            "Updated_Time": null,
            "Updated_User": null,
            "airline": "VARIG Brazilian Airlines",
            "airlinecode": "RG",
            "id": 13,
            "mawb_prefix": "042"
        },
        {
            "Created_Time": null,
            "Created_User": null,
            "Deleted_Indicator": null,
            "Deleted_Time": null,
            "Deleted_User": null,
            "Updated_Time": null,
            "Updated_User": null,
            "airline": "Dragonair",
            "airlinecode": "KA",
            "id": 14,
            "mawb_prefix": "043"
        },
        {
            "Created_Time": null,
            "Created_User": null,
            "Deleted_Indicator": null,
            "Deleted_Time": null,
            "Deleted_User": null,
            "Updated_Time": null,
            "Updated_User": null,
            "airline": "LAN Chile",
            "airlinecode": "LA",
            "id": 15,
            "mawb_prefix": "045"
        },
        {
            "Created_Time": null,
            "Created_User": null,
            "Deleted_Indicator": null,
            "Deleted_Time": null,
            "Deleted_User": null,
            "Updated_Time": null,
            "Updated_User": null,
            "airline": "TAP Air Portugal",
            "airlinecode": "TP",
            "id": 16,
            "mawb_prefix": "047"
        },
        {
            "Created_Time": null,
            "Created_User": null,
            "Deleted_Indicator": null,
            "Deleted_Time": null,
            "Deleted_User": null,
            "Updated_Time": null,
            "Updated_User": null,
            "airline": "Cyprus Airways",
            "airlinecode": "CY",
            "id": 17,
            "mawb_prefix": "048"
        },
        {
            "Created_Time": null,
            "Created_User": null,
            "Deleted_Indicator": null,
            "Deleted_Time": null,
            "Deleted_User": null,
            "Updated_Time": null,
            "Updated_User": null,
            "airline": "Olympic Airways",
            "airlinecode": "OA",
            "id": 18,
            "mawb_prefix": "050"
        },
        {
            "Created_Time": null,
            "Created_User": null,
            "Deleted_Indicator": null,
            "Deleted_Time": null,
            "Deleted_User": null,
            "Updated_Time": null,
            "Updated_User": null,
            "airline": "Aer Lingus Cargo",
            "airlinecode": "EI",
            "id": 19,
            "mawb_prefix": "053"
        },
        {
            "Created_Time": null,
            "Created_User": null,
            "Deleted_Indicator": null,
            "Deleted_Time": null,
            "Deleted_User": null,
            "Updated_Time": null,
            "Updated_User": null,
            "airline": "Alitalia",
            "airlinecode": "AZ",
            "id": 20,
            "mawb_prefix": "055"
        },
        {
            "Created_Time": null,
            "Created_User": null,
            "Deleted_Indicator": null,
            "Deleted_Time": null,
            "Deleted_User": null,
            "Updated_Time": null,
            "Updated_User": null,
            "airline": "Air France",
            "airlinecode": "AF",
            "id": 21,
            "mawb_prefix": "057"
        },
        {
            "Created_Time": null,
            "Created_User": null,
            "Deleted_Indicator": null,
            "Deleted_Time": null,
            "Deleted_User": null,
            "Updated_Time": null,
            "Updated_User": null,
            "airline": "Indian Airlines",
            "airlinecode": "IC",
            "id": 22,
            "mawb_prefix": "058"
        },
        {
            "Created_Time": null,
            "Created_User": null,
            "Deleted_Indicator": null,
            "Deleted_Time": null,
            "Deleted_User": null,
            "Updated_Time": null,
            "Updated_User": null,
            "airline": "Air Seychelles",
            "airlinecode": "HM",
            "id": 23,
            "mawb_prefix": "061"
        },
        {
            "Created_Time": null,
            "Created_User": null,
            "Deleted_Indicator": null,
            "Deleted_Time": null,
            "Deleted_User": null,
            "Updated_Time": null,
            "Updated_User": null,
            "airline": "Czech Airlines",
            "airlinecode": "OK",
            "id": 24,
            "mawb_prefix": "064"
        },
        {
            "Created_Time": null,
            "Created_User": null,
            "Deleted_Indicator": null,
            "Deleted_Time": null,
            "Deleted_User": null,
            "Updated_Time": null,
            "Updated_User": null,
            "airline": "Saudi Arabian Airlines",
            "airlinecode": "SV",
            "id": 25,
            "mawb_prefix": "065"
        },
        {
            "Created_Time": null,
            "Created_User": null,
            "Deleted_Indicator": null,
            "Deleted_Time": null,
            "Deleted_User": null,
            "Updated_Time": null,
            "Updated_User": null,
            "airline": "Syrian Arab Airlines",
            "airlinecode": "RB",
            "id": 26,
            "mawb_prefix": "070"
        },
        {
            "Created_Time": null,
            "Created_User": null,
            "Deleted_Indicator": null,
            "Deleted_Time": null,
            "Deleted_User": null,
            "Updated_Time": null,
            "Updated_User": null,
            "airline": "Ethiopian Airlines",
            "airlinecode": "ET",
            "id": 27,
            "mawb_prefix": "071"
        },
        {
            "Created_Time": null,
            "Created_User": null,
            "Deleted_Indicator": null,
            "Deleted_Time": null,
            "Deleted_User": null,
            "Updated_Time": null,
            "Updated_User": null,
            "airline": "Gulf Air",
            "airlinecode": "GF",
            "id": 28,
            "mawb_prefix": "072"
        },
        {
            "Created_Time": null,
            "Created_User": null,
            "Deleted_Indicator": null,
            "Deleted_Time": null,
            "Deleted_User": null,
            "Updated_Time": null,
            "Updated_User": null,
            "airline": "KLM Cargo",
            "airlinecode": "KL",
            "id": 29,
            "mawb_prefix": "074"
        },
        {
            "Created_Time": null,
            "Created_User": null,
            "Deleted_Indicator": null,
            "Deleted_Time": null,
            "Deleted_User": null,
            "Updated_Time": null,
            "Updated_User": null,
            "airline": "Iberia",
            "airlinecode": "IB",
            "id": 30,
            "mawb_prefix": "075"
        },
        {
            "Created_Time": null,
            "Created_User": null,
            "Deleted_Indicator": null,
            "Deleted_Time": null,
            "Deleted_User": null,
            "Updated_Time": null,
            "Updated_User": null,
            "airline": "Middle East Airlines",
            "airlinecode": "ME",
            "id": 31,
            "mawb_prefix": "076"
        },
        {
            "Created_Time": null,
            "Created_User": null,
            "Deleted_Indicator": null,
            "Deleted_Time": null,
            "Deleted_User": null,
            "Updated_Time": null,
            "Updated_User": null,
            "airline": "Egyptair",
            "airlinecode": "MS",
            "id": 32,
            "mawb_prefix": "077"
        },
        {
            "Created_Time": null,
            "Created_User": null,
            "Deleted_Indicator": null,
            "Deleted_Time": null,
            "Deleted_User": null,
            "Updated_Time": null,
            "Updated_User": null,
            "airline": "Philippine Airlines",
            "airlinecode": "PR",
            "id": 33,
            "mawb_prefix": "079"
        },
        {
            "Created_Time": null,
            "Created_User": null,
            "Deleted_Indicator": null,
            "Deleted_Time": null,
            "Deleted_User": null,
            "Updated_Time": null,
            "Updated_User": null,
            "airline": "Air France",
            "airlinecode": "AF",
            "id": 34,
            "mawb_prefix": "057"
        },
        {
            "Created_Time": null,
            "Created_User": null,
            "Deleted_Indicator": null,
            "Deleted_Time": null,
            "Deleted_User": null,
            "Updated_Time": null,
            "Updated_User": null,
            "airline": "LOT Polish Airlines",
            "airlinecode": "LO",
            "id": 35,
            "mawb_prefix": "080"
        },
        {
            "Created_Time": null,
            "Created_User": null,
            "Deleted_Indicator": null,
            "Deleted_Time": null,
            "Deleted_User": null,
            "Updated_Time": null,
            "Updated_User": null,
            "airline": "Qantas Airways",
            "airlinecode": "QF",
            "id": 36,
            "mawb_prefix": "081"
        },
        {
            "Created_Time": null,
            "Created_User": null,
            "Deleted_Indicator": null,
            "Deleted_Time": null,
            "Deleted_User": null,
            "Updated_Time": null,
            "Updated_User": null,
            "airline": "Brussels Airlines",
            "airlinecode": "SN",
            "id": 37,
            "mawb_prefix": "082"
        },
        {
            "Created_Time": null,
            "Created_User": null,
            "Deleted_Indicator": null,
            "Deleted_Time": null,
            "Deleted_User": null,
            "Updated_Time": null,
            "Updated_User": null,
            "airline": "South African Airways",
            "airlinecode": "SA",
            "id": 38,
            "mawb_prefix": "083"
        },
        {
            "Created_Time": null,
            "Created_User": null,
            "Deleted_Indicator": null,
            "Deleted_Time": null,
            "Deleted_User": null,
            "Updated_Time": null,
            "Updated_User": null,
            "airline": "Air New Zealand",
            "airlinecode": "NZ",
            "id": 39,
            "mawb_prefix": "086"
        },
        {
            "Created_Time": null,
            "Created_User": null,
            "Deleted_Indicator": null,
            "Deleted_Time": null,
            "Deleted_User": null,
            "Updated_Time": null,
            "Updated_User": null,
            "airline": "Kingfisher Airlines",
            "airlinecode": "IT",
            "id": 40,
            "mawb_prefix": "090"
        },
        {
            "Created_Time": null,
            "Created_User": null,
            "Deleted_Indicator": null,
            "Deleted_Time": null,
            "Deleted_User": null,
            "Updated_Time": null,
            "Updated_User": null,
            "airline": "KD Avia",
            "airlinecode": "KD",
            "id": 41,
            "mawb_prefix": "093"
        },
        {
            "Created_Time": null,
            "Created_User": null,
            "Deleted_Indicator": null,
            "Deleted_Time": null,
            "Deleted_User": null,
            "Updated_Time": null,
            "Updated_User": null,
            "airline": "Iran Air",
            "airlinecode": "IR",
            "id": 42,
            "mawb_prefix": "096"
        },
        {
            "Created_Time": null,
            "Created_User": null,
            "Deleted_Indicator": null,
            "Deleted_Time": null,
            "Deleted_User": null,
            "Updated_Time": null,
            "Updated_User": null,
            "airline": "Air India",
            "airlinecode": "AI",
            "id": 43,
            "mawb_prefix": "098"
        },
        {
            "Created_Time": null,
            "Created_User": null,
            "Deleted_Indicator": null,
            "Deleted_Time": null,
            "Deleted_User": null,
            "Updated_Time": null,
            "Updated_User": null,
            "airline": "Finnair",
            "airlinecode": "AY",
            "id": 44,
            "mawb_prefix": "105"
        },
        {
            "Created_Time": null,
            "Created_User": null,
            "Deleted_Indicator": null,
            "Deleted_Time": null,
            "Deleted_User": null,
            "Updated_Time": null,
            "Updated_User": null,
            "airline": "Caribbean Airlines",
            "airlinecode": "BW",
            "id": 45,
            "mawb_prefix": "106"
        },
        {
            "Created_Time": null,
            "Created_User": null,
            "Deleted_Indicator": null,
            "Deleted_Time": null,
            "Deleted_User": null,
            "Updated_Time": null,
            "Updated_User": null,
            "airline": "Icelandair",
            "airlinecode": "FI",
            "id": 46,
            "mawb_prefix": "108"
        },
        {
            "Created_Time": null,
            "Created_User": null,
            "Deleted_Indicator": null,
            "Deleted_Time": null,
            "Deleted_User": null,
            "Updated_Time": null,
            "Updated_User": null,
            "airline": "China Cargo Airlines",
            "airlinecode": "CK",
            "id": 47,
            "mawb_prefix": "112"
        },
        {
            "Created_Time": null,
            "Created_User": null,
            "Deleted_Indicator": null,
            "Deleted_Time": null,
            "Deleted_User": null,
            "Updated_Time": null,
            "Updated_User": null,
            "airline": "EL AL",
            "airlinecode": "LY",
            "id": 48,
            "mawb_prefix": "114"
        },
        {
            "Created_Time": null,
            "Created_User": null,
            "Deleted_Indicator": null,
            "Deleted_Time": null,
            "Deleted_User": null,
            "Updated_Time": null,
            "Updated_User": null,
            "airline": "JAT Airways",
            "airlinecode": "JU",
            "id": 49,
            "mawb_prefix": "115"
        },
        {
            "Created_Time": null,
            "Created_User": null,
            "Deleted_Indicator": null,
            "Deleted_Time": null,
            "Deleted_User": null,
            "Updated_Time": null,
            "Updated_User": null,
            "airline": "SAS-Scandinavian Airlines System",
            "airlinecode": "SK",
            "id": 50,
            "mawb_prefix": "117"
        },
        {
            "Created_Time": null,
            "Created_User": null,
            "Deleted_Indicator": null,
            "Deleted_Time": null,
            "Deleted_User": null,
            "Updated_Time": null,
            "Updated_User": null,
            "airline": "TAAG Angola Airlines",
            "airlinecode": "DT",
            "id": 51,
            "mawb_prefix": "118"
        },
        {
            "Created_Time": null,
            "Created_User": null,
            "Deleted_Indicator": null,
            "Deleted_Time": null,
            "Deleted_User": null,
            "Updated_Time": null,
            "Updated_User": null,
            "airline": "Air ALM",
            "airlinecode": "LM",
            "id": 52,
            "mawb_prefix": "119"
        },
        {
            "Created_Time": null,
            "Created_User": null,
            "Deleted_Indicator": null,
            "Deleted_Time": null,
            "Deleted_User": null,
            "Updated_Time": null,
            "Updated_User": null,
            "airline": "Air Algerie",
            "airlinecode": "AH",
            "id": 53,
            "mawb_prefix": "124"
        },
        {
            "Created_Time": null,
            "Created_User": null,
            "Deleted_Indicator": null,
            "Deleted_Time": null,
            "Deleted_User": null,
            "Updated_Time": null,
            "Updated_User": null,
            "airline": "British Airways",
            "airlinecode": "BA",
            "id": 54,
            "mawb_prefix": "125"
        },
        {
            "Created_Time": null,
            "Created_User": null,
            "Deleted_Indicator": null,
            "Deleted_Time": null,
            "Deleted_User": null,
            "Updated_Time": null,
            "Updated_User": null,
            "airline": "Garuda Indonesia",
            "airlinecode": "GA",
            "id": 55,
            "mawb_prefix": "126"
        },
        {
            "Created_Time": null,
            "Created_User": null,
            "Deleted_Indicator": null,
            "Deleted_Time": null,
            "Deleted_User": null,
            "Updated_Time": null,
            "Updated_User": null,
            "airline": "Martinair Cargo",
            "airlinecode": "MP",
            "id": 56,
            "mawb_prefix": "129"
        },
        {
            "Created_Time": null,
            "Created_User": null,
            "Deleted_Indicator": null,
            "Deleted_Time": null,
            "Deleted_User": null,
            "Updated_Time": null,
            "Updated_User": null,
            "airline": "Japan Airlines",
            "airlinecode": "JL",
            "id": 57,
            "mawb_prefix": "131"
        },
        {
            "Created_Time": null,
            "Created_User": null,
            "Deleted_Indicator": null,
            "Deleted_Time": null,
            "Deleted_User": null,
            "Updated_Time": null,
            "Updated_User": null,
            "airline": "LACSA Airlines of Costa Rica",
            "airlinecode": "LR",
            "id": 58,
            "mawb_prefix": "133"
        },
        {
            "Created_Time": null,
            "Created_User": null,
            "Deleted_Indicator": null,
            "Deleted_Time": null,
            "Deleted_User": null,
            "Updated_Time": null,
            "Updated_User": null,
            "airline": "Aeromexico Cargo",
            "airlinecode": "AM",
            "id": 59,
            "mawb_prefix": "139"
        },
        {
            "Created_Time": null,
            "Created_User": null,
            "Deleted_Indicator": null,
            "Deleted_Time": null,
            "Deleted_User": null,
            "Updated_Time": null,
            "Updated_User": null,
            "airline": "LIAT Airlines",
            "airlinecode": "LI",
            "id": 60,
            "mawb_prefix": "140"
        },
        {
            "Created_Time": null,
            "Created_User": null,
            "Deleted_Indicator": null,
            "Deleted_Time": null,
            "Deleted_User": null,
            "Updated_Time": null,
            "Updated_User": null,
            "airline": "Royal Air Maroc",
            "airlinecode": "AT",
            "id": 61,
            "mawb_prefix": "147"
        },
        {
            "Created_Time": null,
            "Created_User": null,
            "Deleted_Indicator": null,
            "Deleted_Time": null,
            "Deleted_User": null,
            "Updated_Time": null,
            "Updated_User": null,
            "airline": "Libyan Airlines",
            "airlinecode": "LN",
            "id": 62,
            "mawb_prefix": "148"
        },
        {
            "Created_Time": null,
            "Created_User": null,
            "Deleted_Indicator": null,
            "Deleted_Time": null,
            "Deleted_User": null,
            "Updated_Time": null,
            "Updated_User": null,
            "airline": "Qatar Airways",
            "airlinecode": "QR",
            "id": 63,
            "mawb_prefix": "157"
        },
        {
            "Created_Time": null,
            "Created_User": null,
            "Deleted_Indicator": null,
            "Deleted_Time": null,
            "Deleted_User": null,
            "Updated_Time": null,
            "Updated_User": null,
            "airline": "Cathay Pacific Airways",
            "airlinecode": "CX",
            "id": 64,
            "mawb_prefix": "160"
        },
        {
            "Created_Time": null,
            "Created_User": null,
            "Deleted_Indicator": null,
            "Deleted_Time": null,
            "Deleted_User": null,
            "Updated_Time": null,
            "Updated_User": null,
            "airline": "TNT Airways",
            "airlinecode": "3V",
            "id": 65,
            "mawb_prefix": "163"
        },
        {
            "Created_Time": null,
            "Created_User": null,
            "Deleted_Indicator": null,
            "Deleted_Time": null,
            "Deleted_User": null,
            "Updated_Time": null,
            "Updated_User": null,
            "airline": "Adria Airways",
            "airlinecode": "JP",
            "id": 66,
            "mawb_prefix": "165"
        },
        {
            "Created_Time": null,
            "Created_User": null,
            "Deleted_Indicator": null,
            "Deleted_Time": null,
            "Deleted_User": null,
            "Updated_Time": null,
            "Updated_User": null,
            "airline": "Cargolux Airlines",
            "airlinecode": "CV",
            "id": 67,
            "mawb_prefix": "172"
        },
        {
            "Created_Time": null,
            "Created_User": null,
            "Deleted_Indicator": null,
            "Deleted_Time": null,
            "Deleted_User": null,
            "Updated_Time": null,
            "Updated_User": null,
            "airline": "Emirates",
            "airlinecode": "EK",
            "id": 68,
            "mawb_prefix": "176"
        },
        {
            "Created_Time": null,
            "Created_User": null,
            "Deleted_Indicator": null,
            "Deleted_Time": null,
            "Deleted_User": null,
            "Updated_Time": null,
            "Updated_User": null,
            "airline": "Korean Air",
            "airlinecode": "KE",
            "id": 69,
            "mawb_prefix": "180"
        },
        {
            "Created_Time": null,
            "Created_User": null,
            "Deleted_Indicator": null,
            "Deleted_Time": null,
            "Deleted_User": null,
            "Updated_Time": null,
            "Updated_User": null,
            "airline": "Malev Hungarian Airlines",
            "airlinecode": "MA",
            "id": 70,
            "mawb_prefix": "182"
        },
        {
            "Created_Time": null,
            "Created_User": null,
            "Deleted_Indicator": null,
            "Deleted_Time": null,
            "Deleted_User": null,
            "Updated_Time": null,
            "Updated_User": null,
            "airline": "VARIG Brazilian Airlines",
            "airlinecode": "RG",
            "id": 71,
            "mawb_prefix": "183"
        },
        {
            "Created_Time": null,
            "Created_User": null,
            "Deleted_Indicator": null,
            "Deleted_Time": null,
            "Deleted_User": null,
            "Updated_Time": null,
            "Updated_User": null,
            "airline": "Jade Cargo International",
            "airlinecode": "JI",
            "id": 72,
            "mawb_prefix": "189"
        },
        {
            "Created_Time": null,
            "Created_User": null,
            "Deleted_Indicator": null,
            "Deleted_Time": null,
            "Deleted_User": null,
            "Updated_Time": null,
            "Updated_User": null,
            "airline": "Air Jamaica",
            "airlinecode": "JM",
            "id": 73,
            "mawb_prefix": "201"
        },
        {
            "Created_Time": null,
            "Created_User": null,
            "Deleted_Indicator": null,
            "Deleted_Time": null,
            "Deleted_User": null,
            "Updated_Time": null,
            "Updated_User": null,
            "airline": "TACA",
            "airlinecode": "TA",
            "id": 74,
            "mawb_prefix": "202"
        },
        {
            "Created_Time": null,
            "Created_User": null,
            "Deleted_Indicator": null,
            "Deleted_Time": null,
            "Deleted_User": null,
            "Updated_Time": null,
            "Updated_User": null,
            "airline": "ANA All Nippon Cargo",
            "airlinecode": "NH",
            "id": 75,
            "mawb_prefix": "205"
        },
        {
            "Created_Time": null,
            "Created_User": null,
            "Deleted_Indicator": null,
            "Deleted_Time": null,
            "Deleted_User": null,
            "Updated_Time": null,
            "Updated_User": null,
            "airline": "Pakistan Int´l Airlines",
            "airlinecode": "PK",
            "id": 76,
            "mawb_prefix": "214"
        },
        {
            "Created_Time": null,
            "Created_User": null,
            "Deleted_Indicator": null,
            "Deleted_Time": null,
            "Deleted_User": null,
            "Updated_Time": null,
            "Updated_User": null,
            "airline": "Thai Airways",
            "airlinecode": "TG",
            "id": 77,
            "mawb_prefix": "217"
        },
        {
            "Created_Time": null,
            "Created_User": null,
            "Deleted_Indicator": null,
            "Deleted_Time": null,
            "Deleted_User": null,
            "Updated_Time": null,
            "Updated_User": null,
            "airline": "Kuwait Airways",
            "airlinecode": "KU",
            "id": 78,
            "mawb_prefix": "229"
        },
        {
            "Created_Time": null,
            "Created_User": null,
            "Deleted_Indicator": null,
            "Deleted_Time": null,
            "Deleted_User": null,
            "Updated_Time": null,
            "Updated_User": null,
            "airline": "Copa Airlines Cargo",
            "airlinecode": "CM",
            "id": 79,
            "mawb_prefix": "230"
        },
        {
            "Created_Time": null,
            "Created_User": null,
            "Deleted_Indicator": null,
            "Deleted_Time": null,
            "Deleted_User": null,
            "Updated_Time": null,
            "Updated_User": null,
            "airline": "Lauda Air",
            "airlinecode": "NG",
            "id": 80,
            "mawb_prefix": "231"
        },
        {
            "Created_Time": null,
            "Created_User": null,
            "Deleted_Indicator": null,
            "Deleted_Time": null,
            "Deleted_User": null,
            "Updated_Time": null,
            "Updated_User": null,
            "airline": "Malaysian Airline System",
            "airlinecode": "MH",
            "id": 81,
            "mawb_prefix": "232"
        },
        {
            "Created_Time": null,
            "Created_User": null,
            "Deleted_Indicator": null,
            "Deleted_Time": null,
            "Deleted_User": null,
            "Updated_Time": null,
            "Updated_User": null,
            "airline": "Japan Air System",
            "airlinecode": "JD",
            "id": 82,
            "mawb_prefix": "234"
        },
        {
            "Created_Time": null,
            "Created_User": null,
            "Deleted_Indicator": null,
            "Deleted_Time": null,
            "Deleted_User": null,
            "Updated_Time": null,
            "Updated_User": null,
            "airline": "Turkish Airlines",
            "airlinecode": "TK",
            "id": 83,
            "mawb_prefix": "235"
        },
        {
            "Created_Time": null,
            "Created_User": null,
            "Deleted_Indicator": null,
            "Deleted_Time": null,
            "Deleted_User": null,
            "Updated_Time": null,
            "Updated_User": null,
            "airline": "British Midland Airways",
            "airlinecode": "BD",
            "id": 84,
            "mawb_prefix": "236"
        },
        {
            "Created_Time": null,
            "Created_User": null,
            "Deleted_Indicator": null,
            "Deleted_Time": null,
            "Deleted_User": null,
            "Updated_Time": null,
            "Updated_User": null,
            "airline": "Air Mauritius",
            "airlinecode": "MK",
            "id": 85,
            "mawb_prefix": "239"
        },
        {
            "Created_Time": null,
            "Created_User": null,
            "Deleted_Indicator": null,
            "Deleted_Time": null,
            "Deleted_User": null,
            "Updated_Time": null,
            "Updated_User": null,
            "airline": "Austrian Cargo",
            "airlinecode": "OS",
            "id": 86,
            "mawb_prefix": "257"
        },
        {
            "Created_Time": null,
            "Created_User": null,
            "Deleted_Indicator": null,
            "Deleted_Time": null,
            "Deleted_User": null,
            "Updated_Time": null,
            "Updated_User": null,
            "airline": "Air Madagascar",
            "airlinecode": "MD",
            "id": 87,
            "mawb_prefix": "258"
        },
        {
            "Created_Time": null,
            "Created_User": null,
            "Deleted_Indicator": null,
            "Deleted_Time": null,
            "Deleted_User": null,
            "Updated_Time": null,
            "Updated_User": null,
            "airline": "Far Eastern Air Transport",
            "airlinecode": "EF",
            "id": 88,
            "mawb_prefix": "265"
        },
        {
            "Created_Time": null,
            "Created_User": null,
            "Deleted_Indicator": null,
            "Deleted_Time": null,
            "Deleted_User": null,
            "Updated_Time": null,
            "Updated_User": null,
            "airline": "LTU (Leisure Cargo)",
            "airlinecode": "LT",
            "id": 89,
            "mawb_prefix": "266"
        },
        {
            "Created_Time": null,
            "Created_User": null,
            "Deleted_Indicator": null,
            "Deleted_Time": null,
            "Deleted_User": null,
            "Updated_Time": null,
            "Updated_User": null,
            "airline": "Trans Mediterranean Airways",
            "airlinecode": "TL",
            "id": 90,
            "mawb_prefix": "270"
        },
        {
            "Created_Time": null,
            "Created_User": null,
            "Deleted_Indicator": null,
            "Deleted_Time": null,
            "Deleted_User": null,
            "Updated_Time": null,
            "Updated_User": null,
            "airline": "Kalitta Air",
            "airlinecode": "K4",
            "id": 91,
            "mawb_prefix": "272"
        },
        {
            "Created_Time": null,
            "Created_User": null,
            "Deleted_Indicator": null,
            "Deleted_Time": null,
            "Deleted_User": null,
            "Updated_Time": null,
            "Updated_User": null,
            "airline": "Air Hong Kong",
            "airlinecode": "LD",
            "id": 92,
            "mawb_prefix": "288"
        },
        {
            "Created_Time": null,
            "Created_User": null,
            "Deleted_Indicator": null,
            "Deleted_Time": null,
            "Deleted_User": null,
            "Updated_Time": null,
            "Updated_User": null,
            "airline": "China Airlines",
            "airlinecode": "CI",
            "id": 93,
            "mawb_prefix": "297"
        },
        {
            "Created_Time": null,
            "Created_User": null,
            "Deleted_Indicator": null,
            "Deleted_Time": null,
            "Deleted_User": null,
            "Updated_Time": null,
            "Updated_User": null,
            "airline": "Global Aviation and Services",
            "airlinecode": "5S",
            "id": 94,
            "mawb_prefix": "301"
        },
        {
            "Created_Time": null,
            "Created_User": null,
            "Deleted_Indicator": null,
            "Deleted_Time": null,
            "Deleted_User": null,
            "Updated_Time": null,
            "Updated_User": null,
            "airline": "Sky West Airlines",
            "airlinecode": "OO",
            "id": 95,
            "mawb_prefix": "302"
        },
        {
            "Created_Time": null,
            "Created_User": null,
            "Deleted_Indicator": null,
            "Deleted_Time": null,
            "Deleted_User": null,
            "Updated_Time": null,
            "Updated_User": null,
            "airline": "Centurion Air Cargo",
            "airlinecode": "WE",
            "id": 96,
            "mawb_prefix": "307"
        },
        {
            "Created_Time": null,
            "Created_User": null,
            "Deleted_Indicator": null,
            "Deleted_Time": null,
            "Deleted_User": null,
            "Updated_Time": null,
            "Updated_User": null,
            "airline": "Shandong Airlines (Chinese)",
            "airlinecode": "SC",
            "id": 97,
            "mawb_prefix": "324"
        },
        {
            "Created_Time": null,
            "Created_User": null,
            "Deleted_Indicator": null,
            "Deleted_Time": null,
            "Deleted_User": null,
            "Updated_Time": null,
            "Updated_User": null,
            "airline": "Florida West International Airways",
            "airlinecode": "RF",
            "id": 98,
            "mawb_prefix": "330"
        },
        {
            "Created_Time": null,
            "Created_User": null,
            "Deleted_Indicator": null,
            "Deleted_Time": null,
            "Deleted_User": null,
            "Updated_Time": null,
            "Updated_User": null,
            "airline": "Northern Air Cargo",
            "airlinecode": "NC",
            "id": 99,
            "mawb_prefix": "345"
        },
        {
            "Created_Time": null,
            "Created_User": null,
            "Deleted_Indicator": null,
            "Deleted_Time": null,
            "Deleted_User": null,
            "Updated_Time": null,
            "Updated_User": null,
            "airline": "Cargolux Italia",
            "airlinecode": "C8",
            "id": 100,
            "mawb_prefix": "356"
        },
        {
            "Created_Time": null,
            "Created_User": null,
            "Deleted_Indicator": null,
            "Deleted_Time": null,
            "Deleted_User": null,
            "Updated_Time": null,
            "Updated_User": null,
            "airline": "Atlas Air",
            "airlinecode": "5Y",
            "id": 101,
            "mawb_prefix": "369"
        },
        {
            "Created_Time": null,
            "Created_User": null,
            "Deleted_Indicator": null,
            "Deleted_Time": null,
            "Deleted_User": null,
            "Updated_Time": null,
            "Updated_User": null,
            "airline": "Cayman Airways",
            "airlinecode": "KX",
            "id": 102,
            "mawb_prefix": "378"
        },
        {
            "Created_Time": null,
            "Created_User": null,
            "Deleted_Indicator": null,
            "Deleted_Time": null,
            "Deleted_User": null,
            "Updated_Time": null,
            "Updated_User": null,
            "airline": "Aegean Airlines",
            "airlinecode": "A3",
            "id": 103,
            "mawb_prefix": "390"
        },
        {
            "Created_Time": null,
            "Created_User": null,
            "Deleted_Indicator": null,
            "Deleted_Time": null,
            "Deleted_User": null,
            "Updated_Time": null,
            "Updated_User": null,
            "airline": "Polar Air Cargo",
            "airlinecode": "PO",
            "id": 104,
            "mawb_prefix": "403"
        },
        {
            "Created_Time": null,
            "Created_User": null,
            "Deleted_Indicator": null,
            "Deleted_Time": null,
            "Deleted_User": null,
            "Updated_Time": null,
            "Updated_User": null,
            "airline": "Arrow Air",
            "airlinecode": "JW",
            "id": 105,
            "mawb_prefix": "404"
        },
        {
            "Created_Time": null,
            "Created_User": null,
            "Deleted_Indicator": null,
            "Deleted_Time": null,
            "Deleted_User": null,
            "Updated_Time": null,
            "Updated_User": null,
            "airline": "UPS Air Cargo",
            "airlinecode": "5X",
            "id": 106,
            "mawb_prefix": "406"
        },
        {
            "Created_Time": null,
            "Created_User": null,
            "Deleted_Indicator": null,
            "Deleted_Time": null,
            "Deleted_User": null,
            "Updated_Time": null,
            "Updated_User": null,
            "airline": "National Air Cargo",
            "airlinecode": "N8",
            "id": 107,
            "mawb_prefix": "416"
        },
        {
            "Created_Time": null,
            "Created_User": null,
            "Deleted_Indicator": null,
            "Deleted_Time": null,
            "Deleted_User": null,
            "Updated_Time": null,
            "Updated_User": null,
            "airline": "Siberia Airlines",
            "airlinecode": "S7",
            "id": 108,
            "mawb_prefix": "421"
        },
        {
            "Created_Time": null,
            "Created_User": null,
            "Deleted_Indicator": null,
            "Deleted_Time": null,
            "Deleted_User": null,
            "Updated_Time": null,
            "Updated_User": null,
            "airline": "DHL Aviation/DHL Airways",
            "airlinecode": "ER",
            "id": 109,
            "mawb_prefix": "423"
        },
        {
            "Created_Time": null,
            "Created_User": null,
            "Deleted_Indicator": null,
            "Deleted_Time": null,
            "Deleted_User": null,
            "Updated_Time": null,
            "Updated_User": null,
            "airline": "Air Astana",
            "airlinecode": "KC",
            "id": 110,
            "mawb_prefix": "465"
        },
        {
            "Created_Time": null,
            "Created_User": null,
            "Deleted_Indicator": null,
            "Deleted_Time": null,
            "Deleted_User": null,
            "Updated_Time": null,
            "Updated_User": null,
            "airline": "Shenzhen Airlines (Chinese)",
            "airlinecode": "ZH",
            "id": 111,
            "mawb_prefix": "479"
        },
        {
            "Created_Time": null,
            "Created_User": null,
            "Deleted_Indicator": null,
            "Deleted_Time": null,
            "Deleted_User": null,
            "Updated_Time": null,
            "Updated_User": null,
            "airline": "Aeroflot",
            "airlinecode": "SU",
            "id": 112,
            "mawb_prefix": "507"
        },
        {
            "Created_Time": null,
            "Created_User": null,
            "Deleted_Indicator": null,
            "Deleted_Time": null,
            "Deleted_User": null,
            "Updated_Time": null,
            "Updated_User": null,
            "airline": "Royal Jordanian",
            "airlinecode": "RJ",
            "id": 113,
            "mawb_prefix": "512"
        },
        {
            "Created_Time": null,
            "Created_User": null,
            "Deleted_Indicator": null,
            "Deleted_Time": null,
            "Deleted_User": null,
            "Updated_Time": null,
            "Updated_User": null,
            "airline": "Southwest Airlines",
            "airlinecode": "WN",
            "id": 114,
            "mawb_prefix": "526"
        },
        {
            "Created_Time": null,
            "Created_User": null,
            "Deleted_Indicator": null,
            "Deleted_Time": null,
            "Deleted_User": null,
            "Updated_Time": null,
            "Updated_User": null,
            "airline": "Cielos Airlines",
            "airlinecode": "A2",
            "id": 115,
            "mawb_prefix": "529"
        },
        {
            "Created_Time": null,
            "Created_User": null,
            "Deleted_Indicator": null,
            "Deleted_Time": null,
            "Deleted_User": null,
            "Updated_Time": null,
            "Updated_User": null,
            "airline": "ABSA Aerolinhas Brasileiras",
            "airlinecode": "M3",
            "id": 116,
            "mawb_prefix": "549"
        },
        {
            "Created_Time": null,
            "Created_User": null,
            "Deleted_Indicator": null,
            "Deleted_Time": null,
            "Deleted_User": null,
            "Updated_Time": null,
            "Updated_User": null,
            "airline": "Mario’s Air",
            "airlinecode": "M2",
            "id": 117,
            "mawb_prefix": "552"
        },
        {
            "Created_Time": null,
            "Created_User": null,
            "Deleted_Indicator": null,
            "Deleted_Time": null,
            "Deleted_User": null,
            "Updated_Time": null,
            "Updated_User": null,
            "airline": "Sun Express",
            "airlinecode": "XQ",
            "id": 118,
            "mawb_prefix": "564"
        },
        {
            "Created_Time": null,
            "Created_User": null,
            "Deleted_Indicator": null,
            "Deleted_Time": null,
            "Deleted_User": null,
            "Updated_Time": null,
            "Updated_User": null,
            "airline": "Ukraine Int´l Airlines",
            "airlinecode": "PS",
            "id": 119,
            "mawb_prefix": "566"
        },
        {
            "Created_Time": null,
            "Created_User": null,
            "Deleted_Indicator": null,
            "Deleted_Time": null,
            "Deleted_User": null,
            "Updated_Time": null,
            "Updated_User": null,
            "airline": "Air Moldova",
            "airlinecode": "9U",
            "id": 120,
            "mawb_prefix": "572"
        },
        {
            "Created_Time": null,
            "Created_User": null,
            "Deleted_Indicator": null,
            "Deleted_Time": null,
            "Deleted_User": null,
            "Updated_Time": null,
            "Updated_User": null,
            "airline": "Coyne Airways",
            "airlinecode": "7C",
            "id": 121,
            "mawb_prefix": "575"
        },
        {
            "Created_Time": null,
            "Created_User": null,
            "Deleted_Indicator": null,
            "Deleted_Time": null,
            "Deleted_User": null,
            "Updated_Time": null,
            "Updated_User": null,
            "airline": "AirBridge Cargo",
            "airlinecode": "RU",
            "id": 122,
            "mawb_prefix": "580"
        },
        {
            "Created_Time": null,
            "Created_User": null,
            "Deleted_Indicator": null,
            "Deleted_Time": null,
            "Deleted_User": null,
            "Updated_Time": null,
            "Updated_User": null,
            "airline": "Jet Airways",
            "airlinecode": "9W",
            "id": 123,
            "mawb_prefix": "589"
        },
        {
            "Created_Time": null,
            "Created_User": null,
            "Deleted_Indicator": null,
            "Deleted_Time": null,
            "Deleted_User": null,
            "Updated_Time": null,
            "Updated_User": null,
            "airline": "SriLankan Cargo",
            "airlinecode": "UL",
            "id": 124,
            "mawb_prefix": "603"
        },
        {
            "Created_Time": null,
            "Created_User": null,
            "Deleted_Indicator": null,
            "Deleted_Time": null,
            "Deleted_User": null,
            "Updated_Time": null,
            "Updated_User": null,
            "airline": "more AWB tracking",
            "airlinecode": "UL",
            "id": 125,
            "mawb_prefix": "603"
        },
        {
            "Created_Time": null,
            "Created_User": null,
            "Deleted_Indicator": null,
            "Deleted_Time": null,
            "Deleted_User": null,
            "Updated_Time": null,
            "Updated_User": null,
            "airline": "Cameroon Airlines",
            "airlinecode": "UY",
            "id": 126,
            "mawb_prefix": "604"
        },
        {
            "Created_Time": null,
            "Created_User": null,
            "Deleted_Indicator": null,
            "Deleted_Time": null,
            "Deleted_User": null,
            "Updated_Time": null,
            "Updated_User": null,
            "airline": "ETIHAD Airways",
            "airlinecode": "EY",
            "id": 127,
            "mawb_prefix": "607"
        },
        {
            "Created_Time": null,
            "Created_User": null,
            "Deleted_Indicator": null,
            "Deleted_Time": null,
            "Deleted_User": null,
            "Updated_Time": null,
            "Updated_User": null,
            "airline": "DHL Aviation / European Air Transport",
            "airlinecode": "QY",
            "id": 128,
            "mawb_prefix": "615"
        },
        {
            "Created_Time": null,
            "Created_User": null,
            "Deleted_Indicator": null,
            "Deleted_Time": null,
            "Deleted_User": null,
            "Updated_Time": null,
            "Updated_User": null,
            "airline": "Singapore Airlines",
            "airlinecode": "SQ",
            "id": 129,
            "mawb_prefix": "618"
        },
        {
            "Created_Time": null,
            "Created_User": null,
            "Deleted_Indicator": null,
            "Deleted_Time": null,
            "Deleted_User": null,
            "Updated_Time": null,
            "Updated_User": null,
            "airline": "Bulgaria Air",
            "airlinecode": "FB",
            "id": 130,
            "mawb_prefix": "623"
        },
        {
            "Created_Time": null,
            "Created_User": null,
            "Deleted_Indicator": null,
            "Deleted_Time": null,
            "Deleted_User": null,
            "Updated_Time": null,
            "Updated_User": null,
            "airline": "Air Greenland",
            "airlinecode": "GL",
            "id": 131,
            "mawb_prefix": "631"
        },
        {
            "Created_Time": null,
            "Created_User": null,
            "Deleted_Indicator": null,
            "Deleted_Time": null,
            "Deleted_User": null,
            "Updated_Time": null,
            "Updated_User": null,
            "airline": "Yemenia Yemen Airways",
            "airlinecode": "IY",
            "id": 132,
            "mawb_prefix": "635"
        },
        {
            "Created_Time": null,
            "Created_User": null,
            "Deleted_Indicator": null,
            "Deleted_Time": null,
            "Deleted_User": null,
            "Updated_Time": null,
            "Updated_User": null,
            "airline": "Air Malta",
            "airlinecode": "KM",
            "id": 133,
            "mawb_prefix": "643"
        },
        {
            "Created_Time": null,
            "Created_User": null,
            "Deleted_Indicator": null,
            "Deleted_Time": null,
            "Deleted_User": null,
            "Updated_Time": null,
            "Updated_User": null,
            "airline": "Air Niugini",
            "airlinecode": "PX",
            "id": 134,
            "mawb_prefix": "656"
        },
        {
            "Created_Time": null,
            "Created_User": null,
            "Deleted_Indicator": null,
            "Deleted_Time": null,
            "Deleted_User": null,
            "Updated_Time": null,
            "Updated_User": null,
            "airline": "Air Baltic",
            "airlinecode": "BT",
            "id": 135,
            "mawb_prefix": "657"
        },
        {
            "Created_Time": null,
            "Created_User": null,
            "Deleted_Indicator": null,
            "Deleted_Time": null,
            "Deleted_User": null,
            "Updated_Time": null,
            "Updated_User": null,
            "airline": "Royal Brunei Airlines",
            "airlinecode": "BI",
            "id": 136,
            "mawb_prefix": "672"
        },
        {
            "Created_Time": null,
            "Created_User": null,
            "Deleted_Indicator": null,
            "Deleted_Time": null,
            "Deleted_User": null,
            "Updated_Time": null,
            "Updated_User": null,
            "airline": "Air Macau",
            "airlinecode": "NX",
            "id": 137,
            "mawb_prefix": "675"
        },
        {
            "Created_Time": null,
            "Created_User": null,
            "Deleted_Indicator": null,
            "Deleted_Time": null,
            "Deleted_User": null,
            "Updated_Time": null,
            "Updated_User": null,
            "airline": "Eva Airways",
            "airlinecode": "BR",
            "id": 138,
            "mawb_prefix": "695"
        },
        {
            "Created_Time": null,
            "Created_User": null,
            "Deleted_Indicator": null,
            "Deleted_Time": null,
            "Deleted_User": null,
            "Updated_Time": null,
            "Updated_User": null,
            "airline": "CAL Cargo Air Lines",
            "airlinecode": "5C",
            "id": 139,
            "mawb_prefix": "700"
        },
        {
            "Created_Time": null,
            "Created_User": null,
            "Deleted_Indicator": null,
            "Deleted_Time": null,
            "Deleted_User": null,
            "Updated_Time": null,
            "Updated_User": null,
            "airline": "Kenya Airways",
            "airlinecode": "KQ",
            "id": 140,
            "mawb_prefix": "706"
        },
        {
            "Created_Time": null,
            "Created_User": null,
            "Deleted_Indicator": null,
            "Deleted_Time": null,
            "Deleted_User": null,
            "Updated_Time": null,
            "Updated_User": null,
            "airline": "MNG Airlines",
            "airlinecode": "MB",
            "id": 141,
            "mawb_prefix": "716"
        },
        {
            "Created_Time": null,
            "Created_User": null,
            "Deleted_Indicator": null,
            "Deleted_Time": null,
            "Deleted_User": null,
            "Updated_Time": null,
            "Updated_User": null,
            "airline": "Swiss",
            "airlinecode": "LX",
            "id": 142,
            "mawb_prefix": "724"
        },
        {
            "Created_Time": null,
            "Created_User": null,
            "Deleted_Indicator": null,
            "Deleted_Time": null,
            "Deleted_User": null,
            "Updated_Time": null,
            "Updated_User": null,
            "airline": "Tampa Airlines",
            "airlinecode": "QT",
            "id": 143,
            "mawb_prefix": "729"
        },
        {
            "Created_Time": null,
            "Created_User": null,
            "Deleted_Indicator": null,
            "Deleted_Time": null,
            "Deleted_User": null,
            "Updated_Time": null,
            "Updated_User": null,
            "airline": "Xiamen Airlines",
            "airlinecode": "MF",
            "id": 144,
            "mawb_prefix": "731"
        },
        {
            "Created_Time": null,
            "Created_User": null,
            "Deleted_Indicator": null,
            "Deleted_Time": null,
            "Deleted_User": null,
            "Updated_Time": null,
            "Updated_User": null,
            "airline": "SATA Air Acores",
            "airlinecode": "SP",
            "id": 145,
            "mawb_prefix": "737"
        },
        {
            "Created_Time": null,
            "Created_User": null,
            "Deleted_Indicator": null,
            "Deleted_Time": null,
            "Deleted_User": null,
            "Updated_Time": null,
            "Updated_User": null,
            "airline": "Vietnam Airlines",
            "airlinecode": "VN",
            "id": 146,
            "mawb_prefix": "738"
        },
        {
            "Created_Time": null,
            "Created_User": null,
            "Deleted_Indicator": null,
            "Deleted_Time": null,
            "Deleted_User": null,
            "Updated_Time": null,
            "Updated_User": null,
            "airline": "Avient",
            "airlinecode": "SM",
            "id": 147,
            "mawb_prefix": "757"
        },
        {
            "Created_Time": null,
            "Created_User": null,
            "Deleted_Indicator": null,
            "Deleted_Time": null,
            "Deleted_User": null,
            "Updated_Time": null,
            "Updated_User": null,
            "airline": "Azerbaijan Airlines",
            "airlinecode": "J2",
            "id": 148,
            "mawb_prefix": "771"
        },
        {
            "Created_Time": null,
            "Created_User": null,
            "Deleted_Indicator": null,
            "Deleted_Time": null,
            "Deleted_User": null,
            "Updated_Time": null,
            "Updated_User": null,
            "airline": "Shanghai Airlines",
            "airlinecode": "FM",
            "id": 149,
            "mawb_prefix": "774"
        },
        {
            "Created_Time": null,
            "Created_User": null,
            "Deleted_Indicator": null,
            "Deleted_Time": null,
            "Deleted_User": null,
            "Updated_Time": null,
            "Updated_User": null,
            "airline": "China Eastern Airlines",
            "airlinecode": "MU",
            "id": 150,
            "mawb_prefix": "781"
        },
        {
            "Created_Time": null,
            "Created_User": null,
            "Deleted_Indicator": null,
            "Deleted_Time": null,
            "Deleted_User": null,
            "Updated_Time": null,
            "Updated_User": null,
            "airline": "China Southern Airlines",
            "airlinecode": "CZ",
            "id": 151,
            "mawb_prefix": "784"
        },
        {
            "Created_Time": null,
            "Created_User": null,
            "Deleted_Indicator": null,
            "Deleted_Time": null,
            "Deleted_User": null,
            "Updated_Time": null,
            "Updated_User": null,
            "airline": "Grandstar Cargo",
            "airlinecode": "GD",
            "id": 152,
            "mawb_prefix": "800"
        },
        {
            "Created_Time": null,
            "Created_User": null,
            "Deleted_Indicator": null,
            "Deleted_Time": null,
            "Deleted_User": null,
            "Updated_Time": null,
            "Updated_User": null,
            "airline": "Mandarin Airlines",
            "airlinecode": "AE",
            "id": 153,
            "mawb_prefix": "803"
        },
        {
            "Created_Time": null,
            "Created_User": null,
            "Deleted_Indicator": null,
            "Deleted_Time": null,
            "Deleted_User": null,
            "Updated_Time": null,
            "Updated_User": null,
            "airline": "Amerijet International",
            "airlinecode": "M6",
            "id": 154,
            "mawb_prefix": "810"
        },
        {
            "Created_Time": null,
            "Created_User": null,
            "Deleted_Indicator": null,
            "Deleted_Time": null,
            "Deleted_User": null,
            "Updated_Time": null,
            "Updated_User": null,
            "airline": "SAC South American Airways",
            "airlinecode": "S6",
            "id": 155,
            "mawb_prefix": "817"
        },
        {
            "Created_Time": null,
            "Created_User": null,
            "Deleted_Indicator": null,
            "Deleted_Time": null,
            "Deleted_User": null,
            "Updated_Time": null,
            "Updated_User": null,
            "airline": "Shanghai Airlines Cargo",
            "airlinecode": "F4",
            "id": 156,
            "mawb_prefix": "825"
        },
        {
            "Created_Time": null,
            "Created_User": null,
            "Deleted_Indicator": null,
            "Deleted_Time": null,
            "Deleted_User": null,
            "Updated_Time": null,
            "Updated_User": null,
            "airline": "Croatia Airlines",
            "airlinecode": "OU",
            "id": 157,
            "mawb_prefix": "831"
        },
        {
            "Created_Time": null,
            "Created_User": null,
            "Deleted_Indicator": null,
            "Deleted_Time": null,
            "Deleted_User": null,
            "Updated_Time": null,
            "Updated_User": null,
            "airline": "Hong Kong Airlines",
            "airlinecode": "N8",
            "id": 158,
            "mawb_prefix": "851"
        },
        {
            "Created_Time": null,
            "Created_User": null,
            "Deleted_Indicator": null,
            "Deleted_Time": null,
            "Deleted_User": null,
            "Updated_Time": null,
            "Updated_User": null,
            "airline": "Africa West",
            "airlinecode": "FK",
            "id": 159,
            "mawb_prefix": "858"
        },
        {
            "Created_Time": null,
            "Created_User": null,
            "Deleted_Indicator": null,
            "Deleted_Time": null,
            "Deleted_User": null,
            "Updated_Time": null,
            "Updated_User": null,
            "airline": "Atlantic Southeast Airlines",
            "airlinecode": "EV",
            "id": 160,
            "mawb_prefix": "862"
        },
        {
            "Created_Time": null,
            "Created_User": null,
            "Deleted_Indicator": null,
            "Deleted_Time": null,
            "Deleted_User": null,
            "Updated_Time": null,
            "Updated_User": null,
            "airline": "MASAir",
            "airlinecode": "MY",
            "id": 161,
            "mawb_prefix": "865"
        },
        {
            "Created_Time": null,
            "Created_User": null,
            "Deleted_Indicator": null,
            "Deleted_Time": null,
            "Deleted_User": null,
            "Updated_Time": null,
            "Updated_User": null,
            "airline": "Aerosvit",
            "airlinecode": "VV",
            "id": 162,
            "mawb_prefix": "870"
        },
        {
            "Created_Time": null,
            "Created_User": null,
            "Deleted_Indicator": null,
            "Deleted_Time": null,
            "Deleted_User": null,
            "Updated_Time": null,
            "Updated_User": null,
            "airline": "Yangtze River Express Airlines",
            "airlinecode": "Y8",
            "id": 163,
            "mawb_prefix": "871"
        },
        {
            "Created_Time": null,
            "Created_User": null,
            "Deleted_Indicator": null,
            "Deleted_Time": null,
            "Deleted_User": null,
            "Updated_Time": null,
            "Updated_User": null,
            "airline": "AeroUnion",
            "airlinecode": "6R",
            "id": 164,
            "mawb_prefix": "873"
        },
        {
            "Created_Time": null,
            "Created_User": null,
            "Deleted_Indicator": null,
            "Deleted_Time": null,
            "Deleted_User": null,
            "Updated_Time": null,
            "Updated_User": null,
            "airline": "Sichuan Airlines",
            "airlinecode": "3U",
            "id": 165,
            "mawb_prefix": "876"
        },
        {
            "Created_Time": null,
            "Created_User": null,
            "Deleted_Indicator": null,
            "Deleted_Time": null,
            "Deleted_User": null,
            "Updated_Time": null,
            "Updated_User": null,
            "airline": "Hainan Airlines (Chinese)",
            "airlinecode": "HU",
            "id": 166,
            "mawb_prefix": "880"
        },
        {
            "Created_Time": null,
            "Created_User": null,
            "Deleted_Indicator": null,
            "Deleted_Time": null,
            "Deleted_User": null,
            "Updated_Time": null,
            "Updated_User": null,
            "airline": "Condor Flugdienst",
            "airlinecode": "DE",
            "id": 167,
            "mawb_prefix": "881"
        },
        {
            "Created_Time": null,
            "Created_User": null,
            "Deleted_Indicator": null,
            "Deleted_Time": null,
            "Deleted_User": null,
            "Updated_Time": null,
            "Updated_User": null,
            "airline": "Comair",
            "airlinecode": "OH",
            "id": 168,
            "mawb_prefix": "886"
        },
        {
            "Created_Time": null,
            "Created_User": null,
            "Deleted_Indicator": null,
            "Deleted_Time": null,
            "Deleted_User": null,
            "Updated_Time": null,
            "Updated_User": null,
            "airline": "TAB Cargo",
            "airlinecode": "B1",
            "id": 169,
            "mawb_prefix": "901"
        },
        {
            "Created_Time": null,
            "Created_User": null,
            "Deleted_Indicator": null,
            "Deleted_Time": null,
            "Deleted_User": null,
            "Updated_Time": null,
            "Updated_User": null,
            "airline": "Air Armenia",
            "airlinecode": "QN",
            "id": 170,
            "mawb_prefix": "907"
        },
        {
            "Created_Time": null,
            "Created_User": null,
            "Deleted_Indicator": null,
            "Deleted_Time": null,
            "Deleted_User": null,
            "Updated_Time": null,
            "Updated_User": null,
            "airline": "Buraq Air Transport (Arabic only)",
            "airlinecode": "UZ",
            "id": 171,
            "mawb_prefix": "928"
        },
        {
            "Created_Time": null,
            "Created_User": null,
            "Deleted_Indicator": null,
            "Deleted_Time": null,
            "Deleted_User": null,
            "Updated_Time": null,
            "Updated_User": null,
            "airline": "Virgin Atlantic",
            "airlinecode": "VS",
            "id": 172,
            "mawb_prefix": "932"
        },
        {
            "Created_Time": null,
            "Created_User": null,
            "Deleted_Indicator": null,
            "Deleted_Time": null,
            "Deleted_User": null,
            "Updated_Time": null,
            "Updated_User": null,
            "airline": "Nippon Cargo Airlines",
            "airlinecode": "KZ",
            "id": 173,
            "mawb_prefix": "933"
        },
        {
            "Created_Time": null,
            "Created_User": null,
            "Deleted_Indicator": null,
            "Deleted_Time": null,
            "Deleted_User": null,
            "Updated_Time": null,
            "Updated_User": null,
            "airline": "TAM Brazilian Airlines",
            "airlinecode": "JJ",
            "id": 174,
            "mawb_prefix": "957"
        },
        {
            "Created_Time": null,
            "Created_User": null,
            "Deleted_Indicator": null,
            "Deleted_Time": null,
            "Deleted_User": null,
            "Updated_Time": null,
            "Updated_User": null,
            "airline": "Insel Air Cargo",
            "airlinecode": "7I",
            "id": 175,
            "mawb_prefix": "958"
        },
        {
            "Created_Time": null,
            "Created_User": null,
            "Deleted_Indicator": null,
            "Deleted_Time": null,
            "Deleted_User": null,
            "Updated_Time": null,
            "Updated_User": null,
            "airline": "Estonian Air",
            "airlinecode": "OV",
            "id": 176,
            "mawb_prefix": "960"
        },
        {
            "Created_Time": null,
            "Created_User": null,
            "Deleted_Indicator": null,
            "Deleted_Time": null,
            "Deleted_User": null,
            "Updated_Time": null,
            "Updated_User": null,
            "airline": "Aeromexpress Cargo",
            "airlinecode": "QO",
            "id": 177,
            "mawb_prefix": "976"
        },
        {
            "Created_Time": null,
            "Created_User": null,
            "Deleted_Indicator": null,
            "Deleted_Time": null,
            "Deleted_User": null,
            "Updated_Time": null,
            "Updated_User": null,
            "airline": "Asiana Airlines",
            "airlinecode": "OZ",
            "id": 178,
            "mawb_prefix": "988"
        },
        {
            "Created_Time": null,
            "Created_User": null,
            "Deleted_Indicator": null,
            "Deleted_Time": null,
            "Deleted_User": null,
            "Updated_Time": null,
            "Updated_User": null,
            "airline": "Great Wall Airlines",
            "airlinecode": "IJ",
            "id": 179,
            "mawb_prefix": "989"
        },
        {
            "Created_Time": null,
            "Created_User": null,
            "Deleted_Indicator": null,
            "Deleted_Time": null,
            "Deleted_User": null,
            "Updated_Time": null,
            "Updated_User": null,
            "airline": "Air Europa Cargo",
            "airlinecode": "UX",
            "id": 180,
            "mawb_prefix": "996"
        },
        {
            "Created_Time": null,
            "Created_User": null,
            "Deleted_Indicator": null,
            "Deleted_Time": null,
            "Deleted_User": null,
            "Updated_Time": null,
            "Updated_User": null,
            "airline": "Biman Bangladesh",
            "airlinecode": "BG",
            "id": 181,
            "mawb_prefix": "997"
        },
        {
            "Created_Time": null,
            "Created_User": null,
            "Deleted_Indicator": null,
            "Deleted_Time": null,
            "Deleted_User": null,
            "Updated_Time": null,
            "Updated_User": null,
            "airline": "Air China",
            "airlinecode": "CA",
            "id": 182,
            "mawb_prefix": "999"
        },
    {
        "Created_Time": null,
        "Created_User": null,
        "Deleted_Indicator": null,
        "Deleted_Time": null,
        "Deleted_User": null,
        "Updated_Time": null,
        "Updated_User": null,
        "airline": "Pradhaan Air Express Private Ltd",
        "airlinecode": "6P",
        "id": 183,
        "mawb_prefix": "349"
    }
]